imdown/__init__.py
imdown/_version.py
imdown/imdown.py
imdown/tests/test_imdown.py
imdown-0.0.1.dev13.dist-info/LICENSE
imdown-0.0.1.dev13.dist-info/METADATA
imdown-0.0.1.dev13.dist-info/WHEEL
imdown-0.0.1.dev13.dist-info/entry_points.txt
imdown-0.0.1.dev13.dist-info/top_level.txt
imdown-0.0.1.dev13.dist-info/RECORD
