Metadata-Version: 2.1
Name: imdown
Version: 0.0.1.dev13
Summary: Collect images from a directory tree and add them to a markdown file.
Author: Leonard Sasse
Author-email: l.sasse@fz-juelich.de
Project-URL: repository, https://github.com/LeSasse/imdown
Keywords: pandoc,markdown,images
Classifier: Development Status :: 4 - Beta
Classifier: Intended Audience :: Science/Research
Classifier: Intended Audience :: Developers
Classifier: License :: OSI Approved
Classifier: Natural Language :: English
Classifier: Topic :: Software Development
Classifier: Topic :: Scientific/Engineering
Classifier: Topic :: Scientific/Engineering :: Bio-Informatics
Classifier: Operating System :: OS Independent
Classifier: Programming Language :: Python :: 3
Requires-Python: >=3.7
License-File: LICENSE
Provides-Extra: dev
Requires-Dist: tox ; extra == 'dev'
